opentelemetry/__init__.py
opentelemetry/instrumentation/__init__.py
opentelemetry/instrumentation/gunicorn/__init__.py
opentelemetry/instrumentation/gunicorn/py.typed
opentelemetry/instrumentation/gunicorn/version.py
opentelemetry_instrumentation_gunicorn-0.1.0b1.dist-info/METADATA
opentelemetry_instrumentation_gunicorn-0.1.0b1.dist-info/WHEEL
opentelemetry_instrumentation_gunicorn-0.1.0b1.dist-info/entry_points.txt
opentelemetry_instrumentation_gunicorn-0.1.0b1.dist-info/licenses/LICENSE
opentelemetry_instrumentation_gunicorn-0.1.0b1.dist-info/RECORD
